{
	"pages": [
		{
			"path": "pages/index/index",
			"style": {
				"navigationBarTitleText": "我的相册",
				"navigationStyle": "custom",
				"enablePullDownRefresh": true
			}
		},
		{
			"path": "pages/upload/index",
			"style": {
				"navigationBarTitleText": "上传照片",
				"navigationBarTextStyle": "black",
				"navigationBarBackgroundColor": "#FFB6C1"
			}
		},
		{
			"path": "pages/album/index",
			"style": {
				"navigationBarTitleText": "宠物相册",
				"navigationBarTextStyle": "black",
				"navigationBarBackgroundColor": "#FFB6C1"
			}
		},
		{
			"path": "pages/profile/index",
			"style": {
				"navigationBarTitleText": "个人中心",
				"navigationBarTextStyle": "black",
				"navigationBarBackgroundColor": "#FFB6C1"
			}
		},
		{
			"path": "pages/about/index",
			"style": {
				"navigationBarTitleText": "关于我们",
				"navigationBarTextStyle": "black",
				"navigationBarBackgroundColor": "#FFB6C1"
			}
		}
	],
	"globalStyle": {
		"navigationBarTextStyle": "black",
		"navigationBarTitleText": "喵汪兔星河",
		"navigationBarBackgroundColor": "#FFB6C1",
		"backgroundColor": "#FFF5F7",
		"backgroundTextStyle": "dark"
	},
	"tabBar": {
		"color": "#999999",
		"selectedColor": "#FF69B4",
		"borderStyle": "white",
		"backgroundColor": "#FFFFFF",
		"list": [
			{
				"pagePath": "pages/index/index",
				"text": "我的相册"
			},
			{
				"pagePath": "pages/upload/index",
				"text": "上传照片"
			},
			{
				"pagePath": "pages/profile/index",
				"text": "我的"
			}
		]
	},
	"uniIdRouter": {}
}
